{"cameraMode":{"drawMode":0,"name":"Shaded","section":"Shading Mode"},"sceneLighting":true,"audioPlay":false,"sceneViewState":{"showFog":true,"showMaterialUpdate":false,"showSkybox":true,"showFlares":true,"showImageEffects":true,"showParticleSystems":true},"in2DMode":false,"pivot":{"x":2.800909996032715,"y":14.026224136352539,"z":-23.202499389648439},"rotation":{"x":0.047581423074007037,"y":-0.0014977012760937214,"z":0.00007152273610699922,"w":0.9988684058189392},"size":27.134124755859376,"orthographic":false}