{"cameraMode":{"drawMode":0,"name":"Shaded","section":"Shading Mode"},"sceneLighting":true,"audioPlay":false,"sceneViewState":{"showFog":true,"showMaterialUpdate":false,"showSkybox":true,"showFlares":true,"showImageEffects":true,"showParticleSystems":true},"in2DMode":false,"pivot":{"x":1261.3072509765625,"y":148.9032440185547,"z":0.184326171875},"rotation":{"x":-0.04592297226190567,"y":-0.016481852158904077,"z":-0.0007577983196824789,"w":0.9988092184066773},"size":568.9509887695313,"orthographic":false}