{"cameraMode":{"drawMode":0,"name":"Shaded","section":"Shading Mode"},"sceneLighting":true,"audioPlay":false,"sceneViewState":{"showFog":true,"showMaterialUpdate":false,"showSkybox":true,"showFlares":true,"showImageEffects":true,"showParticleSystems":true},"in2DMode":false,"pivot":{"x":-11.27334976196289,"y":8.909819602966309,"z":1.4778761863708497},"rotation":{"x":0.0976276844739914,"y":0.6712434887886047,"z":-0.08985687792301178,"w":0.7292702198028565},"size":9.529208183288575,"orthographic":false}